{
  "version": "0.3.3",
  "flags": {},
  "shapes": [
    {
      "label": "tot",
      "text": "",
      "points": [
        [
          301.67441860465124,
          659.1860465116279
        ],
        [
          366.79069767441877,
          728.953488372093
        ]
      ],
      "group_id": null,
      "shape_type": "rectangle",
      "flags": {}
    },
    {
      "label": "tot",
      "text": "",
      "points": [
        [
          207.48837209302337,
          653.3720930232558
        ],
        [
          273.76744186046517,
          728.953488372093
        ]
      ],
      "group_id": null,
      "shape_type": "rectangle",
      "flags": {}
    },
    {
      "label": "tot",
      "text": "",
      "points": [
        [
          254.0000000000001,
          703.3720930232558
        ],
        [
          312.139534883721,
          775.4651162790698
        ]
      ],
      "group_id": null,
      "shape_type": "rectangle",
      "flags": {}
    },
    {
      "label": "tot",
      "text": "",
      "points": [
        [
          312.139534883721,
          727.7906976744187
        ],
        [
          367.95348837209315,
          795.2325581395348
        ]
      ],
      "group_id": null,
      "shape_type": "rectangle",
      "flags": {}
    },
    {
      "label": "tot",
      "text": "",
      "points": [
        [
          186.55813953488382,
          731.2790697674419
        ],
        [
          252.83720930232573,
          803.3720930232558
        ]
      ],
      "group_id": null,
      "shape_type": "rectangle",
      "flags": {}
    },
    {
      "label": "si",
      "text": "",
      "points": [
        [
          192.37209302325596,
          821.9767441860465
        ],
        [
          265.62790697674427,
          902.2093023255813
        ]
      ],
      "group_id": null,
      "shape_type": "rectangle",
      "flags": {}
    },
    {
      "label": "phao",
      "text": "",
      "points": [
        [
          269.11627906976753,
          891.7441860465116
        ],
        [
          330.7441860465117,
          966.1627906976744
        ]
      ],
      "group_id": null,
      "shape_type": "rectangle",
      "flags": {}
    },
    {
      "label": "ma",
      "text": "",
      "points": [
        [
          204.0000000000001,
          941.7441860465117
        ],
        [
          276.09302325581405,
          1025.4651162790697
        ]
      ],
      "group_id": null,
      "shape_type": "rectangle",
      "flags": {}
    },
    {
      "label": "xe",
      "text": "",
      "points": [
        [
          157.48837209302337,
          899.8837209302326
        ],
        [
          223.76744186046517,
          974.3023255813954
        ]
      ],
      "group_id": null,
      "shape_type": "rectangle",
      "flags": {}
    },
    {
      "label": "tuong",
      "text": "",
      "points": [
        [
          283.06976744186056,
          817.3255813953489
        ],
        [
          350.51162790697686,
          895.2325581395348
        ]
      ],
      "group_id": null,
      "shape_type": "rectangle",
      "flags": {}
    },
    {
      "label": "tot",
      "text": "",
      "points": [
        [
          333.06976744186056,
          458.0232558139535
        ],
        [
          387.7209302325582,
          526.6279069767442
        ]
      ],
      "group_id": null,
      "shape_type": "rectangle",
      "flags": {}
    },
    {
      "label": "tot",
      "text": "",
      "points": [
        [
          169.11627906976753,
          447.5581395348837
        ],
        [
          236.55813953488382,
          518.4883720930233
        ]
      ],
      "group_id": null,
      "shape_type": "rectangle",
      "flags": {}
    },
    {
      "label": "tot",
      "text": "",
      "points": [
        [
          164.4651162790699,
          368.48837209302326
        ],
        [
          229.5813953488373,
          440.5813953488372
        ]
      ],
      "group_id": null,
      "shape_type": "rectangle",
      "flags": {}
    },
    {
      "label": "si",
      "text": "",
      "points": [
        [
          129.5813953488373,
          290.5813953488372
        ],
        [
          200.51162790697686,
          363.83720930232556
        ]
      ],
      "group_id": null,
      "shape_type": "rectangle",
      "flags": {}
    },
    {
      "label": "si",
      "text": "",
      "points": [
        [
          215.62790697674427,
          295.2325581395349
        ],
        [
          280.7441860465117,
          363.83720930232556
        ]
      ],
      "group_id": null,
      "shape_type": "rectangle",
      "flags": {}
    },
    {
      "label": "vua",
      "text": "",
      "points": [
        [
          167.95348837209315,
          224.30232558139534
        ],
        [
          236.55813953488382,
          295.2325581395349
        ]
      ],
      "group_id": null,
      "shape_type": "rectangle",
      "flags": {}
    },
    {
      "label": "phao",
      "text": "",
      "points": [
        [
          240.04651162790708,
          219.65116279069767
        ],
        [
          304.0000000000001,
          290.5813953488372
        ]
      ],
      "group_id": null,
      "shape_type": "rectangle",
      "flags": {}
    },
    {
      "label": "phao",
      "text": "",
      "points": [
        [
          298.186046511628,
          183.60465116279067
        ],
        [
          360.97674418604663,
          258.0232558139535
        ]
      ],
      "group_id": null,
      "shape_type": "rectangle",
      "flags": {}
    },
    {
      "label": "ma",
      "text": "",
      "points": [
        [
          354.0000000000001,
          233.6046511627907
        ],
        [
          413.3023255813955,
          305.69767441860466
        ]
      ],
      "group_id": null,
      "shape_type": "rectangle",
      "flags": {}
    },
    {
      "label": "xe",
      "text": "",
      "points": [
        [
          300.51162790697686,
          262.6744186046512
        ],
        [
          357.4883720930234,
          333.6046511627907
        ]
      ],
      "group_id": null,
      "shape_type": "rectangle",
      "flags": {}
    },
    {
      "label": "xe",
      "text": "",
      "points": [
        [
          290.0465116279071,
          333.6046511627907
        ],
        [
          349.3488372093025,
          403.3720930232558
        ]
      ],
      "group_id": null,
      "shape_type": "rectangle",
      "flags": {}
    },
    {
      "label": "tot",
      "text": "",
      "points": [
        [
          249.34883720930247,
          360.3488372093023
        ],
        [
          315.62790697674427,
          432.4418604651163
        ]
      ],
      "group_id": null,
      "shape_type": "rectangle",
      "flags": {}
    },
    {
      "label": "tuong",
      "text": "",
      "points": [
        [
          395.8604651162792,
          380.1162790697674
        ],
        [
          452.8372093023256,
          451.04651162790697
        ]
      ],
      "group_id": null,
      "shape_type": "rectangle",
      "flags": {}
    },
    {
      "label": "tuong",
      "text": "",
      "points": [
        [
          349.3488372093025,
          320.8139534883721
        ],
        [
          407.4883720930234,
          391.74418604651163
        ]
      ],
      "group_id": null,
      "shape_type": "rectangle",
      "flags": {}
    },
    {
      "label": "ma",
      "text": "",
      "points": [
        [
          338.8837209302327,
          387.09302325581393
        ],
        [
          394.6976744186047,
          456.86046511627904
        ]
      ],
      "group_id": null,
      "shape_type": "rectangle",
      "flags": {}
    }
  ],
  "imagePath": "0388.jpg",
  "imageData": null,
  "imageHeight": 1080,
  "imageWidth": 608
}