{
  "version": "0.3.3",
  "flags": {},
  "shapes": [
    {
      "label": "xe",
      "text": "",
      "points": [
        [
          25.043478260869506,
          1831.217391304348
        ],
        [
          216.34782608695627,
          1992.0869565217392
        ]
      ],
      "group_id": null,
      "shape_type": "rectangle",
      "flags": {}
    },
    {
      "label": "xe",
      "text": "",
      "points": [
        [
          820.6956521739128,
          3392.086956521739
        ],
        [
          1094.6086956521738,
          3674.695652173913
        ]
      ],
      "group_id": null,
      "shape_type": "rectangle",
      "flags": {}
    },
    {
      "label": "xe",
      "text": "",
      "points": [
        [
          2698.95652173913,
          2179.0434782608695
        ],
        [
          2916.347826086956,
          2370.3478260869565
        ]
      ],
      "group_id": null,
      "shape_type": "rectangle",
      "flags": {}
    },
    {
      "label": "xe",
      "text": "",
      "points": [
        [
          1620.6956521739128,
          1187.7391304347827
        ],
        [
          1772.8695652173913,
          1300.7826086956522
        ]
      ],
      "group_id": null,
      "shape_type": "rectangle",
      "flags": {}
    },
    {
      "label": "ma",
      "text": "",
      "points": [
        [
          1720.6956521739128,
          1279.0434782608697
        ],
        [
          1877.2173913043478,
          1392.0869565217392
        ]
      ],
      "group_id": null,
      "shape_type": "rectangle",
      "flags": {}
    },
    {
      "label": "ma",
      "text": "",
      "points": [
        [
          2542.434782608695,
          2013.8260869565217
        ],
        [
          2738.086956521739,
          2187.7391304347825
        ]
      ],
      "group_id": null,
      "shape_type": "rectangle",
      "flags": {}
    },
    {
      "label": "ma",
      "text": "",
      "points": [
        [
          677.2173913043478,
          3165.9999999999995
        ],
        [
          933.7391304347827,
          3418.173913043478
        ]
      ],
      "group_id": null,
      "shape_type": "rectangle",
      "flags": {}
    },
    {
      "label": "ma",
      "text": "",
      "points": [
        [
          85.91304347826076,
          1992.0869565217392
        ],
        [
          294.60869565217376,
          2152.95652173913
        ]
      ],
      "group_id": null,
      "shape_type": "rectangle",
      "flags": {}
    },
    {
      "label": "tuong",
      "text": "",
      "points": [
        [
          159.82608695652175,
          2144.260869565217
        ],
        [
          364.17391304347825,
          2326.869565217391
        ]
      ],
      "group_id": null,
      "shape_type": "rectangle",
      "flags": {}
    },
    {
      "label": "tuong",
      "text": "",
      "points": [
        [
          572.8695652173913,
          2913.8260869565215
        ],
        [
          820.6956521739128,
          3152.95652173913
        ]
      ],
      "group_id": null,
      "shape_type": "rectangle",
      "flags": {}
    },
    {
      "label": "tuong",
      "text": "",
      "points": [
        [
          2377.217391304347,
          1861.6521739130435
        ],
        [
          2568.521739130434,
          2035.5652173913045
        ]
      ],
      "group_id": null,
      "shape_type": "rectangle",
      "flags": {}
    },
    {
      "label": "tuong",
      "text": "",
      "points": [
        [
          1820.6956521739128,
          1379.0434782608697
        ],
        [
          1998.9565217391303,
          1500.7826086956522
        ]
      ],
      "group_id": null,
      "shape_type": "rectangle",
      "flags": {}
    },
    {
      "label": "si",
      "text": "",
      "points": [
        [
          1942.4347826086953,
          1487.7391304347827
        ],
        [
          2125.043478260869,
          1613.8260869565217
        ]
      ],
      "group_id": null,
      "shape_type": "rectangle",
      "flags": {}
    },
    {
      "label": "si",
      "text": "",
      "points": [
        [
          2225.043478260869,
          1726.8695652173913
        ],
        [
          2403.304347826087,
          1887.7391304347827
        ]
      ],
      "group_id": null,
      "shape_type": "rectangle",
      "flags": {}
    },
    {
      "label": "si",
      "text": "",
      "points": [
        [
          438.08695652173924,
          2692.086956521739
        ],
        [
          672.8695652173913,
          2913.8260869565215
        ]
      ],
      "group_id": null,
      "shape_type": "rectangle",
      "flags": {}
    },
    {
      "label": "si",
      "text": "",
      "points": [
        [
          268.52173913043475,
          2300.782608695652
        ],
        [
          485.91304347826076,
          2500.782608695652
        ]
      ],
      "group_id": null,
      "shape_type": "rectangle",
      "flags": {}
    },
    {
      "label": "vua",
      "text": "",
      "points": [
        [
          359.82608695652175,
          2500.782608695652
        ],
        [
          577.2173913043478,
          2696.4347826086955
        ]
      ],
      "group_id": null,
      "shape_type": "rectangle",
      "flags": {}
    },
    {
      "label": "vua",
      "text": "",
      "points": [
        [
          2081.565217391304,
          1605.1304347826087
        ],
        [
          2259.826086956521,
          1748.608695652174
        ]
      ],
      "group_id": null,
      "shape_type": "rectangle",
      "flags": {}
    },
    {
      "label": "phao",
      "text": "",
      "points": [
        [
          1416.3478260869563,
          1387.7391304347827
        ],
        [
          1594.6086956521738,
          1531.217391304348
        ]
      ],
      "group_id": null,
      "shape_type": "rectangle",
      "flags": {}
    },
    {
      "label": "phao",
      "text": "",
      "points": [
        [
          2229.391304347826,
          2226.869565217391
        ],
        [
          2455.478260869565,
          2418.173913043478
        ]
      ],
      "group_id": null,
      "shape_type": "rectangle",
      "flags": {}
    },
    {
      "label": "phao",
      "text": "",
      "points": [
        [
          485.91304347826076,
          1800.7826086956522
        ],
        [
          685.9130434782608,
          1957.304347826087
        ]
      ],
      "group_id": null,
      "shape_type": "rectangle",
      "flags": {}
    },
    {
      "label": "phao",
      "text": "",
      "points": [
        [
          1172.8695652173913,
          2857.3043478260865
        ],
        [
          1420.6956521739128,
          3100.782608695652
        ]
      ],
      "group_id": null,
      "shape_type": "rectangle",
      "flags": {}
    },
    {
      "label": "tot",
      "text": "",
      "points": [
        [
          1542.4347826086957,
          2892.086956521739
        ],
        [
          1772.8695652173913,
          3144.260869565217
        ]
      ],
      "group_id": null,
      "shape_type": "rectangle",
      "flags": {}
    },
    {
      "label": "tot",
      "text": "",
      "points": [
        [
          1255.4782608695652,
          2505.1304347826085
        ],
        [
          1468.5217391304348,
          2726.869565217391
        ]
      ],
      "group_id": null,
      "shape_type": "rectangle",
      "flags": {}
    },
    {
      "label": "tot",
      "text": "",
      "points": [
        [
          994.6086956521738,
          2144.260869565217
        ],
        [
          1207.6521739130433,
          2335.565217391304
        ]
      ],
      "group_id": null,
      "shape_type": "rectangle",
      "flags": {}
    },
    {
      "label": "tot",
      "text": "",
      "points": [
        [
          768.5217391304348,
          1848.608695652174
        ],
        [
          972.8695652173913,
          2018.1739130434783
        ]
      ],
      "group_id": null,
      "shape_type": "rectangle",
      "flags": {}
    },
    {
      "label": "tot",
      "text": "",
      "points": [
        [
          607.6521739130433,
          1583.3913043478262
        ],
        [
          798.9565217391303,
          1735.5652173913045
        ]
      ],
      "group_id": null,
      "shape_type": "rectangle",
      "flags": {}
    },
    {
      "label": "tot",
      "text": "",
      "points": [
        [
          1129.3913043478258,
          1366.0
        ],
        [
          1307.6521739130433,
          1496.4347826086957
        ]
      ],
      "group_id": null,
      "shape_type": "rectangle",
      "flags": {}
    },
    {
      "label": "tot",
      "text": "",
      "points": [
        [
          1355.4782608695652,
          1596.4347826086957
        ],
        [
          1529.3913043478258,
          1735.5652173913045
        ]
      ],
      "group_id": null,
      "shape_type": "rectangle",
      "flags": {}
    },
    {
      "label": "tot",
      "text": "",
      "points": [
        [
          1590.2608695652173,
          1857.304347826087
        ],
        [
          1790.2608695652173,
          2018.1739130434783
        ]
      ],
      "group_id": null,
      "shape_type": "rectangle",
      "flags": {}
    },
    {
      "label": "tot",
      "text": "",
      "points": [
        [
          1846.7826086956522,
          2157.3043478260865
        ],
        [
          2046.7826086956522,
          2344.260869565217
        ]
      ],
      "group_id": null,
      "shape_type": "rectangle",
      "flags": {}
    },
    {
      "label": "tot",
      "text": "",
      "points": [
        [
          2168.521739130434,
          2487.7391304347825
        ],
        [
          2398.95652173913,
          2696.4347826086955
        ]
      ],
      "group_id": null,
      "shape_type": "rectangle",
      "flags": {}
    }
  ],
  "imagePath": "0590.jpg",
  "imageData": null,
  "imageHeight": 4032,
  "imageWidth": 3024
}