{
  "version": "0.3.3",
  "flags": {},
  "shapes": [
    {
      "label": "xe",
      "text": "",
      "points": [
        [
          512.0,
          195.4
        ],
        [
          596.8,
          271.40000000000003
        ]
      ],
      "group_id": null,
      "shape_type": "rectangle",
      "flags": {}
    },
    {
      "label": "xe",
      "text": "",
      "points": [
        [
          700.8,
          359.40000000000003
        ],
        [
          798.4,
          446.6
        ]
      ],
      "group_id": null,
      "shape_type": "rectangle",
      "flags": {}
    },
    {
      "label": "ma",
      "text": "",
      "points": [
        [
          601.6,
          197.79999999999998
        ],
        [
          686.4,
          272.20000000000005
        ]
      ],
      "group_id": null,
      "shape_type": "rectangle",
      "flags": {}
    },
    {
      "label": "vua",
      "text": "",
      "points": [
        [
          508.0,
          275.40000000000003
        ],
        [
          596.8,
          357.8
        ]
      ],
      "group_id": null,
      "shape_type": "rectangle",
      "flags": {}
    },
    {
      "label": "tot",
      "text": "",
      "points": [
        [
          694.4,
          197.0
        ],
        [
          784.0,
          274.6
        ]
      ],
      "group_id": null,
      "shape_type": "rectangle",
      "flags": {}
    },
    {
      "label": "tot",
      "text": "",
      "points": [
        [
          701.6,
          276.20000000000005
        ],
        [
          792.0,
          356.20000000000005
        ]
      ],
      "group_id": null,
      "shape_type": "rectangle",
      "flags": {}
    },
    {
      "label": "tot",
      "text": "",
      "points": [
        [
          826.4,
          465.0
        ],
        [
          930.4000000000001,
          560.2
        ]
      ],
      "group_id": null,
      "shape_type": "rectangle",
      "flags": {}
    },
    {
      "label": "tot",
      "text": "",
      "points": [
        [
          608.0,
          452.20000000000005
        ],
        [
          704.0,
          549.8000000000001
        ]
      ],
      "group_id": null,
      "shape_type": "rectangle",
      "flags": {}
    },
    {
      "label": "tot",
      "text": "",
      "points": [
        [
          602.4,
          357.8
        ],
        [
          698.4,
          446.6
        ]
      ],
      "group_id": null,
      "shape_type": "rectangle",
      "flags": {}
    },
    {
      "label": "phao",
      "text": "",
      "points": [
        [
          599.2,
          273.0
        ],
        [
          697.6,
          357.8
        ]
      ],
      "group_id": null,
      "shape_type": "rectangle",
      "flags": {}
    },
    {
      "label": "phao",
      "text": "",
      "points": [
        [
          798.4,
          281.0
        ],
        [
          892.8,
          361.8
        ]
      ],
      "group_id": null,
      "shape_type": "rectangle",
      "flags": {}
    },
    {
      "label": "tuong",
      "text": "",
      "points": [
        [
          790.4,
          202.6
        ],
        [
          877.6,
          280.20000000000005
        ]
      ],
      "group_id": null,
      "shape_type": "rectangle",
      "flags": {}
    },
    {
      "label": "tuong",
      "text": "",
      "points": [
        [
          504.79999999999995,
          361.8
        ],
        [
          598.4,
          447.40000000000003
        ]
      ],
      "group_id": null,
      "shape_type": "rectangle",
      "flags": {}
    },
    {
      "label": "si",
      "text": "",
      "points": [
        [
          507.20000000000005,
          451.40000000000003
        ],
        [
          600.8,
          546.6
        ]
      ],
      "group_id": null,
      "shape_type": "rectangle",
      "flags": {}
    },
    {
      "label": "si",
      "text": "",
      "points": [
        [
          717.6,
          452.20000000000005
        ],
        [
          816.8,
          549.0
        ]
      ],
      "group_id": null,
      "shape_type": "rectangle",
      "flags": {}
    },
    {
      "label": "si",
      "text": "",
      "points": [
        [
          805.6,
          368.20000000000005
        ],
        [
          908.8,
          457.8
        ]
      ],
      "group_id": null,
      "shape_type": "rectangle",
      "flags": {}
    }
  ],
  "imagePath": "0187.jpg",
  "imageData": null,
  "imageHeight": 750,
  "imageWidth": 1000
}