{
  "version": "0.3.3",
  "flags": {},
  "shapes": [
    {
      "label": "xe",
      "text": "",
      "points": [
        [
          277.0,
          26.0
        ],
        [
          322.0,
          73.0
        ]
      ],
      "group_id": null,
      "shape_type": "rectangle",
      "flags": {}
    },
    {
      "label": "xe",
      "text": "",
      "points": [
        [
          718.0,
          27.0
        ],
        [
          766.0,
          74.0
        ]
      ],
      "group_id": null,
      "shape_type": "rectangle",
      "flags": {}
    },
    {
      "label": "xe",
      "text": "",
      "points": [
        [
          762.0,
          542.0
        ],
        [
          820.0,
          599.0
        ]
      ],
      "group_id": null,
      "shape_type": "rectangle",
      "flags": {}
    },
    {
      "label": "xe",
      "text": "",
      "points": [
        [
          227.0,
          543.0
        ],
        [
          284.0,
          600.0
        ]
      ],
      "group_id": null,
      "shape_type": "rectangle",
      "flags": {}
    },
    {
      "label": "tuong",
      "text": "",
      "points": [
        [
          292.0,
          542.0
        ],
        [
          349.0,
          600.0
        ]
      ],
      "group_id": null,
      "shape_type": "rectangle",
      "flags": {}
    },
    {
      "label": "tuong",
      "text": "",
      "points": [
        [
          690.0,
          540.0
        ],
        [
          748.0,
          598.0
        ]
      ],
      "group_id": null,
      "shape_type": "rectangle",
      "flags": {}
    },
    {
      "label": "tuong",
      "text": "",
      "points": [
        [
          661.0,
          24.0
        ],
        [
          708.0,
          71.0
        ]
      ],
      "group_id": null,
      "shape_type": "rectangle",
      "flags": {}
    },
    {
      "label": "ma",
      "text": "",
      "points": [
        [
          331.0,
          22.0
        ],
        [
          377.0,
          69.0
        ]
      ],
      "group_id": null,
      "shape_type": "rectangle",
      "flags": {}
    },
    {
      "label": "tuong",
      "text": "",
      "points": [
        [
          382.0,
          21.0
        ],
        [
          430.0,
          68.0
        ]
      ],
      "group_id": null,
      "shape_type": "rectangle",
      "flags": {}
    },
    {
      "label": "ma",
      "text": "",
      "points": [
        [
          612.0,
          22.0
        ],
        [
          657.0,
          68.0
        ]
      ],
      "group_id": null,
      "shape_type": "rectangle",
      "flags": {}
    },
    {
      "label": "ma",
      "text": "",
      "points": [
        [
          630.0,
          542.0
        ],
        [
          684.0,
          599.0
        ]
      ],
      "group_id": null,
      "shape_type": "rectangle",
      "flags": {}
    },
    {
      "label": "ma",
      "text": "",
      "points": [
        [
          359.0,
          542.0
        ],
        [
          415.0,
          599.0
        ]
      ],
      "group_id": null,
      "shape_type": "rectangle",
      "flags": {}
    },
    {
      "label": "si",
      "text": "",
      "points": [
        [
          429.0,
          538.0
        ],
        [
          484.0,
          596.0
        ]
      ],
      "group_id": null,
      "shape_type": "rectangle",
      "flags": {}
    },
    {
      "label": "si",
      "text": "",
      "points": [
        [
          564.0,
          543.0
        ],
        [
          620.0,
          600.0
        ]
      ],
      "group_id": null,
      "shape_type": "rectangle",
      "flags": {}
    },
    {
      "label": "si",
      "text": "",
      "points": [
        [
          557.0,
          19.0
        ],
        [
          601.0,
          65.0
        ]
      ],
      "group_id": null,
      "shape_type": "rectangle",
      "flags": {}
    },
    {
      "label": "si",
      "text": "",
      "points": [
        [
          443.0,
          19.0
        ],
        [
          489.0,
          67.0
        ]
      ],
      "group_id": null,
      "shape_type": "rectangle",
      "flags": {}
    },
    {
      "label": "vua",
      "text": "",
      "points": [
        [
          501.0,
          20.0
        ],
        [
          545.0,
          66.0
        ]
      ],
      "group_id": null,
      "shape_type": "rectangle",
      "flags": {}
    },
    {
      "label": "vua",
      "text": "",
      "points": [
        [
          499.0,
          538.0
        ],
        [
          552.0,
          595.0
        ]
      ],
      "group_id": null,
      "shape_type": "rectangle",
      "flags": {}
    },
    {
      "label": "phao",
      "text": "",
      "points": [
        [
          300.0,
          420.0
        ],
        [
          357.0,
          474.0
        ]
      ],
      "group_id": null,
      "shape_type": "rectangle",
      "flags": {}
    },
    {
      "label": "phao",
      "text": "",
      "points": [
        [
          690.0,
          413.0
        ],
        [
          744.0,
          465.0
        ]
      ],
      "group_id": null,
      "shape_type": "rectangle",
      "flags": {}
    },
    {
      "label": "phao",
      "text": "",
      "points": [
        [
          669.0,
          116.0
        ],
        [
          717.0,
          162.0
        ]
      ],
      "group_id": null,
      "shape_type": "rectangle",
      "flags": {}
    },
    {
      "label": "phao",
      "text": "",
      "points": [
        [
          325.0,
          121.0
        ],
        [
          374.0,
          169.0
        ]
      ],
      "group_id": null,
      "shape_type": "rectangle",
      "flags": {}
    },
    {
      "label": "tot",
      "text": "",
      "points": [
        [
          263.0,
          174.0
        ],
        [
          315.0,
          222.0
        ]
      ],
      "group_id": null,
      "shape_type": "rectangle",
      "flags": {}
    },
    {
      "label": "tot",
      "text": "",
      "points": [
        [
          382.0,
          175.0
        ],
        [
          432.0,
          225.0
        ]
      ],
      "group_id": null,
      "shape_type": "rectangle",
      "flags": {}
    },
    {
      "label": "tot",
      "text": "",
      "points": [
        [
          499.0,
          177.0
        ],
        [
          548.0,
          225.0
        ]
      ],
      "group_id": null,
      "shape_type": "rectangle",
      "flags": {}
    },
    {
      "label": "tot",
      "text": "",
      "points": [
        [
          610.0,
          173.0
        ],
        [
          660.0,
          223.0
        ]
      ],
      "group_id": null,
      "shape_type": "rectangle",
      "flags": {}
    },
    {
      "label": "tot",
      "text": "",
      "points": [
        [
          729.0,
          176.0
        ],
        [
          781.0,
          223.0
        ]
      ],
      "group_id": null,
      "shape_type": "rectangle",
      "flags": {}
    },
    {
      "label": "tot",
      "text": "",
      "points": [
        [
          740.0,
          353.0
        ],
        [
          795.0,
          402.0
        ]
      ],
      "group_id": null,
      "shape_type": "rectangle",
      "flags": {}
    },
    {
      "label": "tot",
      "text": "",
      "points": [
        [
          624.0,
          352.0
        ],
        [
          676.0,
          403.0
        ]
      ],
      "group_id": null,
      "shape_type": "rectangle",
      "flags": {}
    },
    {
      "label": "tot",
      "text": "",
      "points": [
        [
          502.0,
          356.0
        ],
        [
          553.0,
          404.0
        ]
      ],
      "group_id": null,
      "shape_type": "rectangle",
      "flags": {}
    },
    {
      "label": "tot",
      "text": "",
      "points": [
        [
          377.0,
          352.0
        ],
        [
          431.0,
          405.0
        ]
      ],
      "group_id": null,
      "shape_type": "rectangle",
      "flags": {}
    },
    {
      "label": "tot",
      "text": "",
      "points": [
        [
          252.0,
          352.0
        ],
        [
          308.0,
          403.0
        ]
      ],
      "group_id": null,
      "shape_type": "rectangle",
      "flags": {}
    }
  ],
  "imagePath": "0267.jpg",
  "imageData": null,
  "imageHeight": 607,
  "imageWidth": 1080
}