{
  "version": "0.3.3",
  "flags": {},
  "shapes": [
    {
      "label": "tot",
      "text": "",
      "points": [
        [
          79.0,
          357.0
        ],
        [
          138.0,
          413.0
        ]
      ],
      "group_id": null,
      "shape_type": "rectangle",
      "flags": {}
    },
    {
      "label": "tot",
      "text": "",
      "points": [
        [
          209.0,
          350.0
        ],
        [
          266.0,
          405.0
        ]
      ],
      "group_id": null,
      "shape_type": "rectangle",
      "flags": {}
    },
    {
      "label": "tot",
      "text": "",
      "points": [
        [
          364.0,
          347.0
        ],
        [
          419.0,
          401.0
        ]
      ],
      "group_id": null,
      "shape_type": "rectangle",
      "flags": {}
    },
    {
      "label": "tot",
      "text": "",
      "points": [
        [
          487.0,
          343.0
        ],
        [
          541.0,
          398.0
        ]
      ],
      "group_id": null,
      "shape_type": "rectangle",
      "flags": {}
    },
    {
      "label": "tot",
      "text": "",
      "points": [
        [
          618.0,
          335.0
        ],
        [
          674.0,
          389.0
        ]
      ],
      "group_id": null,
      "shape_type": "rectangle",
      "flags": {}
    },
    {
      "label": "tot",
      "text": "",
      "points": [
        [
          510.0,
          548.0
        ],
        [
          571.0,
          609.0
        ]
      ],
      "group_id": null,
      "shape_type": "rectangle",
      "flags": {}
    },
    {
      "label": "tot",
      "text": "",
      "points": [
        [
          646.0,
          547.0
        ],
        [
          710.0,
          607.0
        ]
      ],
      "group_id": null,
      "shape_type": "rectangle",
      "flags": {}
    },
    {
      "label": "tot",
      "text": "",
      "points": [
        [
          366.0,
          541.0
        ],
        [
          426.0,
          601.0
        ]
      ],
      "group_id": null,
      "shape_type": "rectangle",
      "flags": {}
    },
    {
      "label": "tot",
      "text": "",
      "points": [
        [
          209.0,
          547.0
        ],
        [
          272.0,
          608.0
        ]
      ],
      "group_id": null,
      "shape_type": "rectangle",
      "flags": {}
    },
    {
      "label": "tot",
      "text": "",
      "points": [
        [
          48.0,
          552.0
        ],
        [
          114.0,
          615.0
        ]
      ],
      "group_id": null,
      "shape_type": "rectangle",
      "flags": {}
    },
    {
      "label": "phao",
      "text": "",
      "points": [
        [
          120.0,
          624.0
        ],
        [
          188.0,
          689.0
        ]
      ],
      "group_id": null,
      "shape_type": "rectangle",
      "flags": {}
    },
    {
      "label": "phao",
      "text": "",
      "points": [
        [
          593.0,
          618.0
        ],
        [
          657.0,
          680.0
        ]
      ],
      "group_id": null,
      "shape_type": "rectangle",
      "flags": {}
    },
    {
      "label": "phao",
      "text": "",
      "points": [
        [
          546.0,
          290.0
        ],
        [
          601.0,
          343.0
        ]
      ],
      "group_id": null,
      "shape_type": "rectangle",
      "flags": {}
    },
    {
      "label": "phao",
      "text": "",
      "points": [
        [
          149.0,
          292.0
        ],
        [
          205.0,
          345.0
        ]
      ],
      "group_id": null,
      "shape_type": "rectangle",
      "flags": {}
    },
    {
      "label": "ma",
      "text": "",
      "points": [
        [
          162.0,
          197.0
        ],
        [
          214.0,
          247.0
        ]
      ],
      "group_id": null,
      "shape_type": "rectangle",
      "flags": {}
    },
    {
      "label": "ma",
      "text": "",
      "points": [
        [
          537.0,
          190.0
        ],
        [
          588.0,
          240.0
        ]
      ],
      "group_id": null,
      "shape_type": "rectangle",
      "flags": {}
    },
    {
      "label": "ma",
      "text": "",
      "points": [
        [
          610.0,
          769.0
        ],
        [
          676.0,
          836.0
        ]
      ],
      "group_id": null,
      "shape_type": "rectangle",
      "flags": {}
    },
    {
      "label": "ma",
      "text": "",
      "points": [
        [
          105.0,
          786.0
        ],
        [
          176.0,
          856.0
        ]
      ],
      "group_id": null,
      "shape_type": "rectangle",
      "flags": {}
    },
    {
      "label": "xe",
      "text": "",
      "points": [
        [
          22.0,
          799.0
        ],
        [
          95.0,
          871.0
        ]
      ],
      "group_id": null,
      "shape_type": "rectangle",
      "flags": {}
    },
    {
      "label": "xe",
      "text": "",
      "points": [
        [
          684.0,
          774.0
        ],
        [
          749.0,
          839.0
        ]
      ],
      "group_id": null,
      "shape_type": "rectangle",
      "flags": {}
    },
    {
      "label": "xe",
      "text": "",
      "points": [
        [
          589.0,
          182.0
        ],
        [
          635.0,
          231.0
        ]
      ],
      "group_id": null,
      "shape_type": "rectangle",
      "flags": {}
    },
    {
      "label": "xe",
      "text": "",
      "points": [
        [
          92.0,
          195.0
        ],
        [
          143.0,
          245.0
        ]
      ],
      "group_id": null,
      "shape_type": "rectangle",
      "flags": {}
    },
    {
      "label": "si",
      "text": "",
      "points": [
        [
          304.0,
          191.0
        ],
        [
          354.0,
          241.0
        ]
      ],
      "group_id": null,
      "shape_type": "rectangle",
      "flags": {}
    },
    {
      "label": "si",
      "text": "",
      "points": [
        [
          417.0,
          189.0
        ],
        [
          468.0,
          237.0
        ]
      ],
      "group_id": null,
      "shape_type": "rectangle",
      "flags": {}
    },
    {
      "label": "si",
      "text": "",
      "points": [
        [
          288.0,
          775.0
        ],
        [
          356.0,
          846.0
        ]
      ],
      "group_id": null,
      "shape_type": "rectangle",
      "flags": {}
    },
    {
      "label": "si",
      "text": "",
      "points": [
        [
          434.0,
          769.0
        ],
        [
          498.0,
          838.0
        ]
      ],
      "group_id": null,
      "shape_type": "rectangle",
      "flags": {}
    },
    {
      "label": "tuong",
      "text": "",
      "points": [
        [
          521.0,
          772.0
        ],
        [
          586.0,
          840.0
        ]
      ],
      "group_id": null,
      "shape_type": "rectangle",
      "flags": {}
    },
    {
      "label": "tuong",
      "text": "",
      "points": [
        [
          198.0,
          784.0
        ],
        [
          267.0,
          856.0
        ]
      ],
      "group_id": null,
      "shape_type": "rectangle",
      "flags": {}
    },
    {
      "label": "tuong",
      "text": "",
      "points": [
        [
          471.0,
          185.0
        ],
        [
          521.0,
          233.0
        ]
      ],
      "group_id": null,
      "shape_type": "rectangle",
      "flags": {}
    },
    {
      "label": "vua",
      "text": "",
      "points": [
        [
          360.0,
          194.0
        ],
        [
          409.0,
          243.0
        ]
      ],
      "group_id": null,
      "shape_type": "rectangle",
      "flags": {}
    },
    {
      "label": "vua",
      "text": "",
      "points": [
        [
          363.0,
          776.0
        ],
        [
          430.0,
          846.0
        ]
      ],
      "group_id": null,
      "shape_type": "rectangle",
      "flags": {}
    }
  ],
  "imagePath": "0419.jpg",
  "imageData": null,
  "imageHeight": 1080,
  "imageWidth": 810
}