{
  "version": "0.3.3",
  "flags": {},
  "shapes": [
    {
      "label": "phao",
      "text": "",
      "points": [
        [
          95.61111111111097,
          217.08333333333326
        ],
        [
          203.94444444444434,
          335.1388888888888
        ]
      ],
      "group_id": null,
      "shape_type": "rectangle",
      "flags": {}
    },
    {
      "label": "phao",
      "text": "",
      "points": [
        [
          87.2777777777776,
          1078.1944444444443
        ],
        [
          188.66666666666652,
          1203.1944444444443
        ]
      ],
      "group_id": null,
      "shape_type": "rectangle",
      "flags": {}
    },
    {
      "label": "tot",
      "text": "",
      "points": [
        [
          199.7777777777776,
          1168.4722222222222
        ],
        [
          290.0555555555553,
          1278.1944444444443
        ]
      ],
      "group_id": null,
      "shape_type": "rectangle",
      "flags": {}
    },
    {
      "label": "tot",
      "text": "",
      "points": [
        [
          209.4999999999999,
          912.9166666666666
        ],
        [
          299.7777777777777,
          1018.4722222222222
        ]
      ],
      "group_id": null,
      "shape_type": "rectangle",
      "flags": {}
    },
    {
      "label": "tot",
      "text": "",
      "points": [
        [
          205.33333333333314,
          669.8611111111111
        ],
        [
          302.5555555555553,
          771.25
        ]
      ],
      "group_id": null,
      "shape_type": "rectangle",
      "flags": {}
    },
    {
      "label": "tot",
      "text": "",
      "points": [
        [
          206.72222222222206,
          385.1388888888888
        ],
        [
          301.16666666666663,
          496.24999999999994
        ]
      ],
      "group_id": null,
      "shape_type": "rectangle",
      "flags": {}
    },
    {
      "label": "tot",
      "text": "",
      "points": [
        [
          203.94444444444434,
          99.02777777777771
        ],
        [
          301.16666666666663,
          228.19444444444437
        ]
      ],
      "group_id": null,
      "shape_type": "rectangle",
      "flags": {}
    },
    {
      "label": "tot",
      "text": "",
      "points": [
        [
          458.111111111111,
          224.02777777777771
        ],
        [
          527.5555555555553,
          314.3055555555555
        ]
      ],
      "group_id": null,
      "shape_type": "rectangle",
      "flags": {}
    },
    {
      "label": "tot",
      "text": "",
      "points": [
        [
          446.9999999999999,
          433.74999999999994
        ],
        [
          513.6666666666666,
          524.0277777777777
        ]
      ],
      "group_id": null,
      "shape_type": "rectangle",
      "flags": {}
    },
    {
      "label": "tot",
      "text": "",
      "points": [
        [
          442.83333333333314,
          650.4166666666666
        ],
        [
          508.111111111111,
          737.9166666666666
        ]
      ],
      "group_id": null,
      "shape_type": "rectangle",
      "flags": {}
    },
    {
      "label": "tot",
      "text": "",
      "points": [
        [
          442.83333333333314,
          844.8611111111111
        ],
        [
          506.72222222222206,
          930.9722222222222
        ]
      ],
      "group_id": null,
      "shape_type": "rectangle",
      "flags": {}
    },
    {
      "label": "tot",
      "text": "",
      "points": [
        [
          435.8888888888888,
          1044.861111111111
        ],
        [
          502.5555555555553,
          1136.5277777777778
        ]
      ],
      "group_id": null,
      "shape_type": "rectangle",
      "flags": {}
    },
    {
      "label": "phao",
      "text": "",
      "points": [
        [
          492.83333333333314,
          922.6388888888888
        ],
        [
          552.5555555555553,
          1011.5277777777777
        ]
      ],
      "group_id": null,
      "shape_type": "rectangle",
      "flags": {}
    },
    {
      "label": "phao",
      "text": "",
      "points": [
        [
          517.8333333333331,
          339.3055555555555
        ],
        [
          577.5555555555553,
          425.41666666666663
        ]
      ],
      "group_id": null,
      "shape_type": "rectangle",
      "flags": {}
    },
    {
      "label": "xe",
      "text": "",
      "points": [
        [
          602.5555555555553,
          271.24999999999994
        ],
        [
          665.0555555555553,
          353.1944444444444
        ]
      ],
      "group_id": null,
      "shape_type": "rectangle",
      "flags": {}
    },
    {
      "label": "xe",
      "text": "",
      "points": [
        [
          595.611111111111,
          974.0277777777777
        ],
        [
          645.611111111111,
          1047.638888888889
        ]
      ],
      "group_id": null,
      "shape_type": "rectangle",
      "flags": {}
    },
    {
      "label": "ma",
      "text": "",
      "points": [
        [
          584.4999999999999,
          893.4722222222222
        ],
        [
          640.0555555555553,
          971.25
        ]
      ],
      "group_id": null,
      "shape_type": "rectangle",
      "flags": {}
    },
    {
      "label": "ma",
      "text": "",
      "points": [
        [
          608.111111111111,
          362.91666666666663
        ],
        [
          659.4999999999999,
          440.6944444444444
        ]
      ],
      "group_id": null,
      "shape_type": "rectangle",
      "flags": {}
    },
    {
      "label": "tuong",
      "text": "",
      "points": [
        [
          598.3888888888888,
          451.8055555555555
        ],
        [
          659.4999999999999,
          519.8611111111111
        ]
      ],
      "group_id": null,
      "shape_type": "rectangle",
      "flags": {}
    },
    {
      "label": "tuong",
      "text": "",
      "points": [
        [
          584.4999999999999,
          808.75
        ],
        [
          645.611111111111,
          886.5277777777777
        ]
      ],
      "group_id": null,
      "shape_type": "rectangle",
      "flags": {}
    },
    {
      "label": "si",
      "text": "",
      "points": [
        [
          598.3888888888888,
          708.75
        ],
        [
          653.9444444444442,
          785.1388888888888
        ]
      ],
      "group_id": null,
      "shape_type": "rectangle",
      "flags": {}
    },
    {
      "label": "vua",
      "text": "",
      "points": [
        [
          595.611111111111,
          633.75
        ],
        [
          649.7777777777777,
          705.9722222222222
        ]
      ],
      "group_id": null,
      "shape_type": "rectangle",
      "flags": {}
    }
  ],
  "imagePath": "0513.jpg",
  "imageData": null,
  "imageHeight": 1280,
  "imageWidth": 719
}